jupyterlab_wipp_plugin_creator/__init__.py
jupyterlab_wipp_plugin_creator/_version.py
jupyterlab_wipp_plugin_creator/dockerfile.j2
jupyterlab_wipp_plugin_creator/handlers.py
jupyterlab_wipp_plugin_creator/log.py
jupyterlab_wipp_plugin_creator/labextension/build_log.json
jupyterlab_wipp_plugin_creator/labextension/package.json
jupyterlab_wipp_plugin_creator/labextension/static/lib_index_js.f14e57649e2de539cbd3.js
jupyterlab_wipp_plugin_creator/labextension/static/lib_index_js.f14e57649e2de539cbd3.js.map
jupyterlab_wipp_plugin_creator/labextension/static/node_modules_polusai_jupyterlab-rjsf_lib_fields_codemirror_index_js.743a91165efb8694471d.js
jupyterlab_wipp_plugin_creator/labextension/static/node_modules_polusai_jupyterlab-rjsf_lib_fields_codemirror_index_js.743a91165efb8694471d.js.map
jupyterlab_wipp_plugin_creator/labextension/static/node_modules_polusai_jupyterlab-rjsf_lib_fields_jsonobject_index_js.79c7be949f317b358918.js
jupyterlab_wipp_plugin_creator/labextension/static/node_modules_polusai_jupyterlab-rjsf_lib_fields_jsonobject_index_js.79c7be949f317b358918.js.map
jupyterlab_wipp_plugin_creator/labextension/static/node_modules_polusai_jupyterlab-rjsf_lib_fields_markdown_index_js.2d4a969447c492f68497.js
jupyterlab_wipp_plugin_creator/labextension/static/node_modules_polusai_jupyterlab-rjsf_lib_fields_markdown_index_js.2d4a969447c492f68497.js.map
jupyterlab_wipp_plugin_creator/labextension/static/node_modules_polusai_jupyterlab-rjsf_lib_fields_xml_index_js.c2f56dd409c6b0fe6644.js
jupyterlab_wipp_plugin_creator/labextension/static/node_modules_polusai_jupyterlab-rjsf_lib_fields_xml_index_js.c2f56dd409c6b0fe6644.js.map
jupyterlab_wipp_plugin_creator/labextension/static/remoteEntry.2079c94430ce5d95ad3d.js
jupyterlab_wipp_plugin_creator/labextension/static/remoteEntry.2079c94430ce5d95ad3d.js.map
jupyterlab_wipp_plugin_creator/labextension/static/style.js
jupyterlab_wipp_plugin_creator/labextension/static/style_index_js.5582c7331781b6c0885e.js
jupyterlab_wipp_plugin_creator-0.2.5.dist-info/LICENSE
jupyterlab_wipp_plugin_creator-0.2.5.dist-info/METADATA
jupyterlab_wipp_plugin_creator-0.2.5.dist-info/WHEEL
jupyterlab_wipp_plugin_creator-0.2.5.dist-info/top_level.txt
jupyterlab_wipp_plugin_creator-0.2.5.dist-info/RECORD
