Metadata-Version: 2.1
Name: jupyterlab-wipp-plugin-creator
Version: 0.2.5
Summary: Create WIPP container for local Python code
Home-page: https://github.com/LabShare/jupyterlab-extensions/tree/master/jupyterlab_wipp_plugin_creator
Author: Will Xiao
Author-email: Will.Xiao@axleinfo.com
License: MIT
Keywords: Jupyter,JupyterLab,JupyterLab3
Platform: Linux
Platform: Mac OS X
Platform: Windows
Classifier: License :: OSI Approved :: MIT License
Classifier: Programming Language :: Python
Classifier: Programming Language :: Python :: 3
Classifier: Programming Language :: Python :: 3.6
Classifier: Programming Language :: Python :: 3.7
Classifier: Programming Language :: Python :: 3.8
Classifier: Programming Language :: Python :: 3.9
Classifier: Framework :: Jupyter
Requires-Python: >=3.6
License-File: LICENSE
Requires-Dist: jupyter-server (<2,>=1.6)
Requires-Dist: wipp-client
Requires-Dist: kubernetes
